hun_date_parser/__init__.py
hun_date_parser/utils.py
hun_date_parser/date_parser/__init__.py
hun_date_parser/date_parser/date_parsers.py
hun_date_parser/date_parser/datetime_extractor.py
hun_date_parser/date_parser/patterns.py
hun_date_parser/date_parser/structure_parsers.py
hun_date_parser/date_parser/time_parsers.py
hun_date_parser/date_textualizer/__init__.py
hun_date_parser/date_textualizer/date2text.py
hun_date_parser/date_textualizer/datetime_textualizer.py
hun_date_parser/date_textualizer/time2text.py
test/__init__.py
test/test_date_parsers.py
test/test_datetime2text.py
test/test_datetime_extractor.py
test/test_structure_parsers.py
test/test_time_parsers.py
test/test_utils.py
hun_date_parser_nsoma97-0.0.1.dist-info/LICENSE
hun_date_parser_nsoma97-0.0.1.dist-info/METADATA
hun_date_parser_nsoma97-0.0.1.dist-info/WHEEL
hun_date_parser_nsoma97-0.0.1.dist-info/top_level.txt
hun_date_parser_nsoma97-0.0.1.dist-info/RECORD
