Metadata-Version: 2.1
Name: hun-date-parser-nsoma97
Version: 0.0.1
Summary: A tool for extracting datetime intervals from Hungarian sentences and turning datetime objects into Hungarian text.
Home-page: https://github.com/nsoma97/hun-date-parser
Author: Soma Nagy
Author-email: nagysomabalint@gmail.com
License: UNKNOWN
Platform: UNKNOWN
Classifier: Programming Language :: Python :: 3
Classifier: License :: OSI Approved :: Apache Software License
Classifier: Operating System :: OS Independent
Requires-Python: >=3.6
